dpi_maps/__init__.py
dpi_maps/__main__.py
dpi_maps/main.py
dpi_maps/scrapers.py
dpi_maps-0.0.2.dist-info/METADATA
dpi_maps-0.0.2.dist-info/WHEEL
dpi_maps-0.0.2.dist-info/entry_points.txt
dpi_maps-0.0.2.dist-info/RECORD
